plancton/__init__.py
plancton/daemon.py
plancton/influxdb_streamer.py
plancton-0.6.0.data/scripts/plancton-bootstrap
plancton-0.6.0.data/scripts/planctonctl
plancton-0.6.0.dist-info/DESCRIPTION.rst
plancton-0.6.0.dist-info/METADATA
plancton-0.6.0.dist-info/RECORD
plancton-0.6.0.dist-info/WHEEL
plancton-0.6.0.dist-info/metadata.json
plancton-0.6.0.dist-info/top_level.txt
