Metadata-Version: 2.0
Name: plancton
Version: 0.6.0
Summary: An opportunistic distributed computing project based on Docker
Home-page: https://github.com/mconcas/plancton
Author: Matteo Concas
Author-email: matteo.concas@cern.ch
License: GPL
Keywords: HEP Computing
Platform: UNKNOWN
Classifier: Development Status :: 3 - Alpha
Classifier: Intended Audience :: System Administrators
Classifier: Topic :: Scientific/Engineering :: Physics
Classifier: License :: OSI Approved :: GNU General Public License v3 (GPLv3)
Classifier: Programming Language :: Python :: 2.6
Classifier: Programming Language :: Python :: 2.7
Requires-Dist: docker-py
Requires-Dist: prettytable
Requires-Dist: pyyaml
